Workbook

Sheet Предпосылки
A1: ЗАНЯТИЕ 4.1 — АНАЛИЗ ЧУВСТВИТЕЛЬНОСТИ ФИНАНСОВОЙ МОДЕЛИ
A2: Учебная модель упрощена намеренно: методика финансового расчета не является предметом занятия. Изменяемые предпосылки выделены желтым фоном и синим шрифтом. Таблицы данных Excel размещены на том же листе, что и входные ячейки: это техническое ограничение инструмента.
A4: Базовые предпосылки | E4: Однофакторная таблица: цена | H4: Однофакторная таблица: ставка | K4: Эластичность результата
A5: Параметр | B5: Значение | C5: Единица | E5: Цена, руб./ед. | F5: =Модель!$B$5 -> 39602574 | H5: Ставка | I5: =Модель!$B$5 -> 39602574 | K5: Показатель | L5: База X | M5: X +10% | N5: NPV +10% | O5: Эластичность
A6: Объем продаж, год 1 | B6: 80000 | C6: ед. | E6: 900 | H6: 0.08 | K6: Цена | L6: =$B$7 -> 1200 | M6: =L6*1.1 -> 1320 | N6: =IF(F27="","",F27) | O6: =IF(N6="","",((N6-$B$19)/$B$19)/10%)
A7: Цена, год 1 | B7: 1200 | C7: руб./ед. | E7: 950 | H7: 0.1 | K7: Объем | L7: =$B$6 -> 80000 | M7: =L7*1.1 -> 88000 | N7: =IF(I27="","",I27) | O7: =IF(N7="","",((N7-$B$19)/$B$19)/10%)
A8: Рост объема | B8: 0.04 | C8: %/год | E8: 1000 | H8: 0.12 | K8: Переменные затраты | L8: =$B$10 -> 700 | M8: =L8*1.1 -> 770 | N8: =IF(L27="","",L27) | O8: =IF(N8="","",((N8-$B$19)/$B$19)/10%)
A9: Рост цены | B9: 0.03 | C9: %/год | E9: 1050 | H9: 0.14 | K9: Постоянные затраты | L9: =$B$12 -> 18000000 | M9: =L9*1.1 -> 19800000 | N9: =IF(O27="","",O27) | O9: =IF(N9="","",((N9-$B$19)/$B$19)/10%)
A10: Переменные затраты, год 1 | B10: 700 | C10: руб./ед. | E10: 1100 | H10: 0.16 | K10: CAPEX | L10: =$B$15 -> 30000000 | M10: =L10*1.1 -> 33000000 | N10: =IF(R27="","",R27) | O10: =IF(N10="","",((N10-$B$19)/$B$19)/10%)
A11: Рост переменных затрат | B11: 0.03 | C11: %/год | E11: 1150 | H11: 0.18
A12: Постоянные затраты, год 1 | B12: 18000000 | C12: руб. | E12: 1200 | H12: 0.2 | K12: Эластичность = относительное изменение результата / относительное изменение предпосылки. Знак показывает направление, модуль — силу реакции. Показатель локален и зависит от базовой точки.
A13: Рост постоянных затрат | B13: 0.04 | C13: %/год | E13: 1250 | H13: 0.22
A14: Налоговая ставка | B14: 0.2 | C14: % | E14: 1300 | H14: 0.24
A15: Первоначальный CAPEX | B15: 30000000 | C15: руб. | E15: 1350
A16: Ставка дисконтирования | B16: 0.15 | C16: % | E16: 1400 | H16: Вертикальная таблица: «Подставлять значения по столбцам в» = $B$16. Ставка изменяется в процентных пунктах; не путать ±2 п.п. и ±2 %.
E17: 1450
A18: Контроль модели | B18: Значение | C18: Комментарий | E18: 1500
A19: NPV базового варианта | B19: =Модель!$B$5 -> 39602574 | C19: Должно совпадать с листом «Модель»
A20: Изменение предпосылки | C20: После анализа вернуть базовое значение | E20: Практика: выделить E5:F18 → Данные → Анализ «что если» → Таблица данных. Значения расположены вертикально, поэтому указать «Подставлять значения по столбцам в» = $B$7.
E23: Мини-таблицы данных для tornado chart: Low / Base / High
E24: Цена | F24: =Модель!$B$5 -> 39602574 | H24: Объем | I24: =Модель!$B$5 -> 39602574 | K24: Переменные затраты | L24: =Модель!$B$5 -> 39602574 | N24: Постоянные затраты | O24: =Модель!$B$5 -> 39602574 | Q24: CAPEX | R24: =Модель!$B$5 -> 39602574 | T24: Ставка дисконтирования | U24: =Модель!$B$5 -> 39602574
E25: 1080 | H25: 72000 | K25: 630 | N25: 16200000 | Q25: 27000000 | T25: 0.13
E26: 1200 | H26: 80000 | K26: 700 | N26: 18000000 | Q26: 30000000 | T26: 0.15
E27: 1320 | H27: 88000 | K27: 770 | N27: 19800000 | Q27: 33000000 | T27: 0.17
E29: Для каждой пары выделить четыре ячейки по вертикали вместе с формулой NPV и выполнить «Таблица данных». В качестве ячейки подстановки выбрать соответствующую исходную предпосылку в столбце B. Для ставки используются 13 %, 15 %, 17 %: это ±2 процентных пункта.

Sheet Модель
A1: УПРОЩЕННАЯ ФИНАНСОВАЯ МОДЕЛЬ
A2: Цель листа — единый расчетный результат для анализа чувствительности. Модель учебная: FCF = операционная прибыль после налога; амортизация, оборотный капитал и иные элементы не рассматриваются.
A4: Ключевой показатель | B4: Значение
A5: NPV проекта, руб. | B5: =SUM(B19:G19) -> 39602574
A6: Базовая ставка дисконтирования | B6: =Предпосылки!$B$16 -> 0.15
A8: Показатель | B8: Год 0 | C8: Год 1 | D8: Год 2 | E8: Год 3 | F8: Год 4 | G8: Год 5
A9: Объем, ед. | B9: 0 | C9: =Предпосылки!$B$6 -> 80000 | D9: =C9*(1+Предпосылки!$B$8) -> 83200 | E9: =D9*(1+Предпосылки!$B$8) -> 86528 | F9: =E9*(1+Предпосылки!$B$8) -> 89989.12 | G9: =F9*(1+Предпосылки!$B$8) -> 93588.685
A10: Цена, руб./ед. | B10: 0 | C10: =Предпосылки!$B$7 -> 1200 | D10: =C10*(1+Предпосылки!$B$9) -> 1236 | E10: =D10*(1+Предпосылки!$B$9) -> 1273.08 | F10: =E10*(1+Предпосылки!$B$9) -> 1311.2724 | G10: =F10*(1+Предпосылки!$B$9) -> 1350.6106
A11: Выручка, руб. | B11: 0 | C11: =C9*C10 -> 96000000 | D11: =D9*D10 -> 102835200 | E11: =E9*E10 -> 1.1015707e+08 | F11: =F9*F10 -> 1.1800025e+08 | G11: =G9*G10 -> 1.2640187e+08
A12: Переменные затраты, руб./ед. | B12: 0 | C12: =Предпосылки!$B$10 -> 700 | D12: =C12*(1+Предпосылки!$B$11) -> 721 | E12: =D12*(1+Предпосылки!$B$11) -> 742.63 | F12: =E12*(1+Предпосылки!$B$11) -> 764.9089 | G12: =F12*(1+Предпосылки!$B$11) -> 787.85617
A13: Переменные затраты, руб. | B13: 0 | C13: =C9*C12 -> 56000000 | D13: =D9*D12 -> 59987200 | E13: =E9*E12 -> 64258289 | F13: =F9*F12 -> 68833479 | G13: =G9*G12 -> 73734422
A14: Постоянные затраты, руб. | B14: 0 | C14: =Предпосылки!$B$12 -> 18000000 | D14: =C14*(1+Предпосылки!$B$13) -> 18720000 | E14: =D14*(1+Предпосылки!$B$13) -> 19468800 | F14: =E14*(1+Предпосылки!$B$13) -> 20247552 | G14: =F14*(1+Предпосылки!$B$13) -> 21057454
A15: Операционная прибыль, руб. | B15: 0 | C15: =C11-C13-C14 -> 22000000 | D15: =D11-D13-D14 -> 24128000 | E15: =E11-E13-E14 -> 26429978 | F15: =F11-F13-F14 -> 28919219 | G15: =G11-G13-G14 -> 31609991
A16: Налог, руб. | B16: 0 | C16: =MAX(C15,0)*Предпосылки!$B$14 -> 4400000 | D16: =MAX(D15,0)*Предпосылки!$B$14 -> 4825600 | E16: =MAX(E15,0)*Предпосылки!$B$14 -> 5285995.5 | F16: =MAX(F15,0)*Предпосылки!$B$14 -> 5783843.7 | G16: =MAX(G15,0)*Предпосылки!$B$14 -> 6321998.1
A17: FCF, руб. | B17: =-Предпосылки!$B$15 -> -30000000 | C17: =C15-C16 -> 17600000 | D17: =D15-D16 -> 19302400 | E17: =E15-E16 -> 21143982 | F17: =F15-F16 -> 23135375 | G17: =G15-G16 -> 25287992
A18: Коэффициент дисконтирования | B18: 1 | C18: =1/(1+Предпосылки!$B$16)^1 -> 0.86956522 | D18: =1/(1+Предпосылки!$B$16)^2 -> 0.75614367 | E18: =1/(1+Предпосылки!$B$16)^3 -> 0.65751623 | F18: =1/(1+Предпосылки!$B$16)^4 -> 0.57175325 | G18: =1/(1+Предпосылки!$B$16)^5 -> 0.49717674
A19: PV FCF, руб. | B19: =B17*B18 -> -30000000 | C19: =C17*C18 -> 15304348 | D19: =D17*D18 -> 14595388 | E19: =E17*E18 -> 13902511 | F19: =F17*F18 -> 13227726 | G19: =G17*G18 -> 12572602

Sheet Торнадо
A1: ИСТОЧНИК ДАННЫХ ДЛЯ TORNADO CHART
A2: Таблица заполняется автоматически после создания шести мини-таблиц данных на листе «Предпосылки». Для графика используются отклонения от базового NPV, а не абсолютные уровни NPV.
A4: Фактор | B4: NPV Low | C4: NPV Base | D4: NPV High | E4: Δ Low | F4: Δ High | G4: Макс. эффект | H4: Ранг / сортировка
A5: Цена | B5: =IF(Предпосылки!F25="","",Предпосылки!F25) | C5: =IF(Предпосылки!F26="","",Предпосылки!F26) | D5: =IF(Предпосылки!F27="","",Предпосылки!F27) | E5: =IF(B5="","",B5-Модель!$B$5) | F5: =IF(D5="","",D5-Модель!$B$5) | G5: =IF(E5="","",MAX(ABS(E5),ABS(F5)))
A6: Объем | B6: =IF(Предпосылки!I25="","",Предпосылки!I25) | C6: =IF(Предпосылки!I26="","",Предпосылки!I26) | D6: =IF(Предпосылки!I27="","",Предпосылки!I27) | E6: =IF(B6="","",B6-Модель!$B$5) | F6: =IF(D6="","",D6-Модель!$B$5) | G6: =IF(E6="","",MAX(ABS(E6),ABS(F6)))
A7: Переменные затраты | B7: =IF(Предпосылки!L25="","",Предпосылки!L25) | C7: =IF(Предпосылки!L26="","",Предпосылки!L26) | D7: =IF(Предпосылки!L27="","",Предпосылки!L27) | E7: =IF(B7="","",B7-Модель!$B$5) | F7: =IF(D7="","",D7-Модель!$B$5) | G7: =IF(E7="","",MAX(ABS(E7),ABS(F7)))
A8: Постоянные затраты | B8: =IF(Предпосылки!O25="","",Предпосылки!O25) | C8: =IF(Предпосылки!O26="","",Предпосылки!O26) | D8: =IF(Предпосылки!O27="","",Предпосылки!O27) | E8: =IF(B8="","",B8-Модель!$B$5) | F8: =IF(D8="","",D8-Модель!$B$5) | G8: =IF(E8="","",MAX(ABS(E8),ABS(F8)))
A9: CAPEX | B9: =IF(Предпосылки!R25="","",Предпосылки!R25) | C9: =IF(Предпосылки!R26="","",Предпосылки!R26) | D9: =IF(Предпосылки!R27="","",Предпосылки!R27) | E9: =IF(B9="","",B9-Модель!$B$5) | F9: =IF(D9="","",D9-Модель!$B$5) | G9: =IF(E9="","",MAX(ABS(E9),ABS(F9)))
A10: Ставка дисконтирования | B10: =IF(Предпосылки!U25="","",Предпосылки!U25) | C10: =IF(Предпосылки!U26="","",Предпосылки!U26) | D10: =IF(Предпосылки!U27="","",Предпосылки!U27) | E10: =IF(B10="","",B10-Модель!$B$5) | F10: =IF(D10="","",D10-Модель!$B$5) | G10: =IF(E10="","",MAX(ABS(E10),ABS(F10)))
A12: Построение: после заполнения таблицы отсортировать строки по «Макс. эффект» по убыванию. Для диаграммы выбрать «Фактор», «Δ Low» и «Δ High» → линейчатая диаграмма с группировкой. Ось должна проходить через 0; отрицательное отклонение идет влево, положительное — вправо.

Sheet Задания
A1: ЗАДАНИЯ ЗАНЯТИЯ 4.1
A2: Работа выполняется в файле занятия. Таблица данных Excel — это инструмент анализа «что если», а не структурированная таблица Ctrl+T. Лист «Преподавателю» перед передачей группе удаляется.
A4: № | B4: Задание | C4: Контроль | D4: Результат / вывод | E4: Статус | F4: Примечание
A5: 1 | B5: Проверить базовый вариант модели и вернуть все предпосылки к исходным значениям. | C5: NPV = 39 602 574 руб. | F5: Не начинать чувствительность на измененной базе.
A6: 2 | B6: Построить однофакторную таблицу данных по цене в диапазоне 900–1 500 руб./ед. с шагом 50. | C6: При 1 000 руб. NPV < 0; при 1 050 руб. NPV > 0 | F6: Вертикальный список → ячейка подстановки по столбцам = Предпосылки!B7.
A7: 3 | B7: По таблице цены определить интервал, внутри которого NPV меняет знак. Не использовать Goal Seek. | C7: Критическая цена лежит между 1 000 и 1 050 руб./ед. | F7: Точное критическое значение — тема занятия 4.2.
A8: 4 | B8: Построить однофакторную таблицу по ставке дисконтирования от 8 % до 24 % с шагом 2 п.п. Сравнить форму отклика с ценой. | C8: NPV при 8 % ≈ 53,85 млн; при 24 % ≈ 26,25 млн | F8: Шаг задается в процентных пунктах.
A9: 5 | B9: Рассчитать эластичность NPV к цене при увеличении цены на 10 %. | C9: Эластичность ≈ 7,35x | F9: Интерпретация: +1 % цены около базы дает примерно +7,35 % NPV при прочих равных.
A10: 6 | B10: Создать шесть мини-таблиц данных Low / Base / High для факторов tornado chart. | C10: Во всех строках Base NPV одинаков: 39 602 574 руб. | F10: Для ставки: 13 %, 15 %, 17 %; для остальных факторов — ±10 %.
A11: 7 | B11: На листе «Торнадо» проверить отклонения от базы и отсортировать факторы по максимальному абсолютному эффекту. | C11: Топ-3: Цена → Переменные затраты → Объем | F11: Ранжируется эффект выбранного диапазона, а не вероятность изменения.
A12: 8 | B12: Построить tornado chart по Δ Low и Δ High. Использовать линейчатую диаграмму, ось через ноль. | C12: Цена: примерно ±29,12 млн руб. | F12: Не строить tornado по абсолютным NPV — общий базовый уровень скроет различия.
A13: 9 | B13: Сформулировать три вывода: самый чувствительный фактор; фактор с обратным направлением; ограничение интерпретации tornado chart. | C13: Цена; затраты имеют обратный знак; результат зависит от заданных диапазонов. | F13: Не приписывать графику вероятностный смысл.
A14: 10 | B14: Повышенный уровень: построить второй tornado с более узкими диапазонами и сравнить порядок факторов. | C14: Порядок может измениться | F14: Это демонстрирует зависимость рейтинга от выбранного диапазона.
